percolate_rocks-0.1.0.dist-info/METADATA
percolate_rocks-0.1.0.dist-info/WHEEL
percolate_rocks-0.1.0.dist-info/entry_points.txt
rem_db/__init__.py
rem_db/_rust.abi3.so
rem_db/async_api.py
rem_db/cli.py
rem_db/models.py
percolate_rocks-0.1.0.dist-info/RECORD
