Metadata-Version: 2.4
Name: percolate-rocks
Version: 0.1.0
Classifier: Development Status :: 3 - Alpha
Classifier: Intended Audience :: Developers
Classifier: License :: OSI Approved :: MIT License
Classifier: Programming Language :: Python :: 3
Classifier: Programming Language :: Python :: 3.8
Classifier: Programming Language :: Python :: 3.9
Classifier: Programming Language :: Python :: 3.10
Classifier: Programming Language :: Python :: 3.11
Classifier: Programming Language :: Python :: 3.12
Classifier: Programming Language :: Rust
Requires-Dist: pydantic>=2.0
Requires-Dist: typer>=0.12
Requires-Dist: rich>=13.0
Requires-Dist: pytest>=8.0 ; extra == 'dev'
Requires-Dist: pytest-asyncio>=0.24 ; extra == 'dev'
Requires-Dist: maturin>=1.7 ; extra == 'dev'
Provides-Extra: dev
Summary: High-performance embedded database for semantic search, graph queries, and structured data
Keywords: database,vector-search,graph,embedding,semantic
Author: Percolate Team
License: MIT
Requires-Python: >=3.8
